{
  "op": "create_event_plan",
  "input": {
    "dstPolicy": {
      "gap": "earliest",
      "overlap": "earliest"
    },
    "timeZone": "America/New_York",
    "calendarId": "c",
    "draft": {
      "end": {
        "year": 2025,
        "month": 1,
        "day": 2,
        "hour": 10,
        "minute": 0,
        "second": 0
      },
      "timeZone": "America/New_York",
      "calendarId": "c",
      "id": "e1",
      "start": {
        "year": 2025,
        "month": 1,
        "day": 2,
        "hour": 9,
        "minute": 0,
        "second": 0
      }
    }
  },
  "expected": {
    "meta": {
      "engine": "calendar-tool",
      "engineVersion": "0.1.2",
      "icu": "none",
      "policyVersion": "2026.1",
      "schemaVersion": "0.1",
      "tzdata": "2025b"
    },
    "ok": true,
    "result": {
      "plan": {
        "event": {
          "availability": "busy",
          "calendarId": "c",
          "end": {
            "epochMs": 1735830000000
          },
          "id": "e1",
          "isAllDay": false,
          "start": {
            "epochMs": 1735826400000
          },
          "status": "confirmed",
          "timeZone": "America/New_York"
        },
        "idempotencyKey": "279fd5e5cf4bced27249def7edb86da1ddfe8d000495ce829e2c0ddca706b6ea",
        "inputHash": "64c8f6d863061bbb7cb1b16deac5f86626b7e7caa7ca2d41c62f33e16a008b5f",
        "op": "create",
        "planId": "279fd5e5cf4bced27249def7edb86da1ddfe8d000495ce829e2c0ddca706b6ea"
      },
      "policyProfile": "default",
      "policyVersion": "2026.1"
    }
  }
}
