{
  "op": "expand_recurrence",
  "input": {
    "master": {
      "id": "m",
      "calendarId": "c",
      "start": {
        "year": 2025,
        "month": 1,
        "day": 1,
        "hour": 9,
        "minute": 0,
        "second": 0
      },
      "end": {
        "year": 2025,
        "month": 1,
        "day": 1,
        "hour": 9,
        "minute": 30,
        "second": 0
      },
      "timeZone": "America/New_York",
      "recurrenceRule": {
        "frequency": "DAILY",
        "count": 10
      }
    },
    "dstPolicy": {
      "gap": "earliest",
      "overlap": "earliest"
    },
    "window": {
      "start": {
        "epochMs": 1735862400000
      },
      "end": {
        "epochMs": 1736121600000
      }
    }
  },
  "expected": {
    "meta": {
      "engine": "calendar-tool",
      "engineVersion": "0.1.2",
      "icu": "none",
      "policyVersion": "2026.1",
      "schemaVersion": "0.1",
      "tzdata": "2025b"
    },
    "ok": true,
    "result": {
      "occurrences": [
        {
          "calendarId": "c",
          "endInstant": {
            "epochMs": 1735914600000
          },
          "id": "m",
          "originalStart": {
            "epochMs": 1735912800000
          },
          "source": "recurrence",
          "startInstant": {
            "epochMs": 1735912800000
          }
        },
        {
          "calendarId": "c",
          "endInstant": {
            "epochMs": 1736001000000
          },
          "id": "m",
          "originalStart": {
            "epochMs": 1735999200000
          },
          "source": "recurrence",
          "startInstant": {
            "epochMs": 1735999200000
          }
        },
        {
          "calendarId": "c",
          "endInstant": {
            "epochMs": 1736087400000
          },
          "id": "m",
          "originalStart": {
            "epochMs": 1736085600000
          },
          "source": "recurrence",
          "startInstant": {
            "epochMs": 1736085600000
          }
        }
      ]
    }
  }
}
